[
{
    "arguments": [
        "clang",
        "-Wno-documentation-unknown-command",
        "-Wno-unknown-warning-option",
        "-Wno-unknown-pragmas",
        "-nostdinc",
        "-nostdinc++",
        "-std=gnu++1z",
        "-Wall",
        "-Wextra",
        "-Wextra",
        "-fexceptions",
        "-mthreads",
        "-fsyntax-only",
        "-m64",
        "--target=x86_64-w64-mingw32",
        "-DUNICODE",
        "-D_UNICODE",
        "-DWIN32",
        "-DMINGW_HAS_SECURE_API",
        "-DQT_NO_DEBUG",
        "-DQT_WIDGETS_LIB",
        "-DQT_GUI_LIB",
        "-DQT_CORE_LIB",
        "-DQT_NEEDS_QMAIN",
        "-DQ_CREATOR_RUN",
        "-IC:\\Qt\\Tools\\QtCreator\\share\\qtcreator\\cplusplus\\wrappedMingwHeaders",
        "-IC:\\Qt\\Tools\\QtCreator\\share\\qtcreator\\cplusplus\\wrappedQtHeaders",
        "-IC:\\Qt\\Tools\\QtCreator\\share\\qtcreator\\cplusplus\\wrappedQtHeaders\\QtCore",
        "-IC:\\Users\\vanish\\Desktop\\курсач\\course_work",
        "-IC:\\Qt\\6.4.0\\mingw_64\\include",
        "-IC:\\Qt\\6.4.0\\mingw_64\\include\\QtWidgets",
        "-IC:\\Qt\\6.4.0\\mingw_64\\include\\QtGui",
        "-IC:\\Qt\\6.4.0\\mingw_64\\include\\QtCore",
        "-IC:\\Users\\vanish\\Desktop\\курсач\\build-course_work-Desktop_Qt_6_4_0_MinGW_64_bit-Release\\release",
        "-IC:\\Users\\vanish\\Desktop\\курсач\\build-course_work-Desktop_Qt_6_4_0_MinGW_64_bit-Release",
        "-IC:\\Qt\\6.4.0\\mingw_64\\mkspecs\\win32-g++",
        "-isystem",
        "C:\\Qt\\Tools\\mingw1120_64\\lib\\gcc\\x86_64-w64-mingw32\\11.2.0\\include\\c++",
        "-isystem",
        "C:\\Qt\\Tools\\mingw1120_64\\lib\\gcc\\x86_64-w64-mingw32\\11.2.0\\include\\c++\\x86_64-w64-mingw32",
        "-isystem",
        "C:\\Qt\\Tools\\mingw1120_64\\lib\\gcc\\x86_64-w64-mingw32\\11.2.0\\include\\c++\\backward",
        "-isystem",
        "C:\\Qt\\Tools\\QtCreator\\bin\\clang\\lib\\clang\\14.0.3\\include",
        "-isystem",
        "C:\\Qt\\Tools\\mingw1120_64\\x86_64-w64-mingw32\\include",
        "-fmessage-length=0",
        "-fdiagnostics-show-note-include-stack",
        "-fretain-comments-from-system-headers",
        "-fmacro-backtrace-limit=0",
        "-ferror-limit=1000",
        "-x",
        "c++",
        "C:\\Users\\vanish\\Desktop\\курсач\\course_work\\adddialog.cpp"
    ],
    "directory": "C:/Users/vanish/Desktop/курсач/build-course_work-Desktop_Qt_6_4_0_MinGW_64_bit-Release/.qtc_clangd",
    "file": "C:/Users/vanish/Desktop/курсач/course_work/adddialog.cpp"
},
{
    "arguments": [
        "clang",
        "-Wno-documentation-unknown-command",
        "-Wno-unknown-warning-option",
        "-Wno-unknown-pragmas",
        "-nostdinc",
        "-nostdinc++",
        "-std=gnu++1z",
        "-Wall",
        "-Wextra",
        "-Wextra",
        "-fexceptions",
        "-mthreads",
        "-fsyntax-only",
        "-m64",
        "--target=x86_64-w64-mingw32",
        "-DUNICODE",
        "-D_UNICODE",
        "-DWIN32",
        "-DMINGW_HAS_SECURE_API",
        "-DQT_NO_DEBUG",
        "-DQT_WIDGETS_LIB",
        "-DQT_GUI_LIB",
        "-DQT_CORE_LIB",
        "-DQT_NEEDS_QMAIN",
        "-DQ_CREATOR_RUN",
        "-IC:\\Qt\\Tools\\QtCreator\\share\\qtcreator\\cplusplus\\wrappedMingwHeaders",
        "-IC:\\Qt\\Tools\\QtCreator\\share\\qtcreator\\cplusplus\\wrappedQtHeaders",
        "-IC:\\Qt\\Tools\\QtCreator\\share\\qtcreator\\cplusplus\\wrappedQtHeaders\\QtCore",
        "-IC:\\Users\\vanish\\Desktop\\курсач\\course_work",
        "-IC:\\Qt\\6.4.0\\mingw_64\\include",
        "-IC:\\Qt\\6.4.0\\mingw_64\\include\\QtWidgets",
        "-IC:\\Qt\\6.4.0\\mingw_64\\include\\QtGui",
        "-IC:\\Qt\\6.4.0\\mingw_64\\include\\QtCore",
        "-IC:\\Users\\vanish\\Desktop\\курсач\\build-course_work-Desktop_Qt_6_4_0_MinGW_64_bit-Release\\release",
        "-IC:\\Users\\vanish\\Desktop\\курсач\\build-course_work-Desktop_Qt_6_4_0_MinGW_64_bit-Release",
        "-IC:\\Qt\\6.4.0\\mingw_64\\mkspecs\\win32-g++",
        "-isystem",
        "C:\\Qt\\Tools\\mingw1120_64\\lib\\gcc\\x86_64-w64-mingw32\\11.2.0\\include\\c++",
        "-isystem",
        "C:\\Qt\\Tools\\mingw1120_64\\lib\\gcc\\x86_64-w64-mingw32\\11.2.0\\include\\c++\\x86_64-w64-mingw32",
        "-isystem",
        "C:\\Qt\\Tools\\mingw1120_64\\lib\\gcc\\x86_64-w64-mingw32\\11.2.0\\include\\c++\\backward",
        "-isystem",
        "C:\\Qt\\Tools\\QtCreator\\bin\\clang\\lib\\clang\\14.0.3\\include",
        "-isystem",
        "C:\\Qt\\Tools\\mingw1120_64\\x86_64-w64-mingw32\\include",
        "-fmessage-length=0",
        "-fdiagnostics-show-note-include-stack",
        "-fretain-comments-from-system-headers",
        "-fmacro-backtrace-limit=0",
        "-ferror-limit=1000",
        "-x",
        "c++",
        "C:\\Users\\vanish\\Desktop\\курсач\\course_work\\addresswidget.cpp"
    ],
    "directory": "C:/Users/vanish/Desktop/курсач/build-course_work-Desktop_Qt_6_4_0_MinGW_64_bit-Release/.qtc_clangd",
    "file": "C:/Users/vanish/Desktop/курсач/course_work/addresswidget.cpp"
},
{
    "arguments": [
        "clang",
        "-Wno-documentation-unknown-command",
        "-Wno-unknown-warning-option",
        "-Wno-unknown-pragmas",
        "-nostdinc",
        "-nostdinc++",
        "-std=gnu++1z",
        "-Wall",
        "-Wextra",
        "-Wextra",
        "-fexceptions",
        "-mthreads",
        "-fsyntax-only",
        "-m64",
        "--target=x86_64-w64-mingw32",
        "-DUNICODE",
        "-D_UNICODE",
        "-DWIN32",
        "-DMINGW_HAS_SECURE_API",
        "-DQT_NO_DEBUG",
        "-DQT_WIDGETS_LIB",
        "-DQT_GUI_LIB",
        "-DQT_CORE_LIB",
        "-DQT_NEEDS_QMAIN",
        "-DQ_CREATOR_RUN",
        "-IC:\\Qt\\Tools\\QtCreator\\share\\qtcreator\\cplusplus\\wrappedMingwHeaders",
        "-IC:\\Qt\\Tools\\QtCreator\\share\\qtcreator\\cplusplus\\wrappedQtHeaders",
        "-IC:\\Qt\\Tools\\QtCreator\\share\\qtcreator\\cplusplus\\wrappedQtHeaders\\QtCore",
        "-IC:\\Users\\vanish\\Desktop\\курсач\\course_work",
        "-IC:\\Qt\\6.4.0\\mingw_64\\include",
        "-IC:\\Qt\\6.4.0\\mingw_64\\include\\QtWidgets",
        "-IC:\\Qt\\6.4.0\\mingw_64\\include\\QtGui",
        "-IC:\\Qt\\6.4.0\\mingw_64\\include\\QtCore",
        "-IC:\\Users\\vanish\\Desktop\\курсач\\build-course_work-Desktop_Qt_6_4_0_MinGW_64_bit-Release\\release",
        "-IC:\\Users\\vanish\\Desktop\\курсач\\build-course_work-Desktop_Qt_6_4_0_MinGW_64_bit-Release",
        "-IC:\\Qt\\6.4.0\\mingw_64\\mkspecs\\win32-g++",
        "-isystem",
        "C:\\Qt\\Tools\\mingw1120_64\\lib\\gcc\\x86_64-w64-mingw32\\11.2.0\\include\\c++",
        "-isystem",
        "C:\\Qt\\Tools\\mingw1120_64\\lib\\gcc\\x86_64-w64-mingw32\\11.2.0\\include\\c++\\x86_64-w64-mingw32",
        "-isystem",
        "C:\\Qt\\Tools\\mingw1120_64\\lib\\gcc\\x86_64-w64-mingw32\\11.2.0\\include\\c++\\backward",
        "-isystem",
        "C:\\Qt\\Tools\\QtCreator\\bin\\clang\\lib\\clang\\14.0.3\\include",
        "-isystem",
        "C:\\Qt\\Tools\\mingw1120_64\\x86_64-w64-mingw32\\include",
        "-fmessage-length=0",
        "-fdiagnostics-show-note-include-stack",
        "-fretain-comments-from-system-headers",
        "-fmacro-backtrace-limit=0",
        "-ferror-limit=1000",
        "-x",
        "c++",
        "C:\\Users\\vanish\\Desktop\\курсач\\course_work\\finddialog.cpp"
    ],
    "directory": "C:/Users/vanish/Desktop/курсач/build-course_work-Desktop_Qt_6_4_0_MinGW_64_bit-Release/.qtc_clangd",
    "file": "C:/Users/vanish/Desktop/курсач/course_work/finddialog.cpp"
},
{
    "arguments": [
        "clang",
        "-Wno-documentation-unknown-command",
        "-Wno-unknown-warning-option",
        "-Wno-unknown-pragmas",
        "-nostdinc",
        "-nostdinc++",
        "-std=gnu++1z",
        "-Wall",
        "-Wextra",
        "-Wextra",
        "-fexceptions",
        "-mthreads",
        "-fsyntax-only",
        "-m64",
        "--target=x86_64-w64-mingw32",
        "-DUNICODE",
        "-D_UNICODE",
        "-DWIN32",
        "-DMINGW_HAS_SECURE_API",
        "-DQT_NO_DEBUG",
        "-DQT_WIDGETS_LIB",
        "-DQT_GUI_LIB",
        "-DQT_CORE_LIB",
        "-DQT_NEEDS_QMAIN",
        "-DQ_CREATOR_RUN",
        "-IC:\\Qt\\Tools\\QtCreator\\share\\qtcreator\\cplusplus\\wrappedMingwHeaders",
        "-IC:\\Qt\\Tools\\QtCreator\\share\\qtcreator\\cplusplus\\wrappedQtHeaders",
        "-IC:\\Qt\\Tools\\QtCreator\\share\\qtcreator\\cplusplus\\wrappedQtHeaders\\QtCore",
        "-IC:\\Users\\vanish\\Desktop\\курсач\\course_work",
        "-IC:\\Qt\\6.4.0\\mingw_64\\include",
        "-IC:\\Qt\\6.4.0\\mingw_64\\include\\QtWidgets",
        "-IC:\\Qt\\6.4.0\\mingw_64\\include\\QtGui",
        "-IC:\\Qt\\6.4.0\\mingw_64\\include\\QtCore",
        "-IC:\\Users\\vanish\\Desktop\\курсач\\build-course_work-Desktop_Qt_6_4_0_MinGW_64_bit-Release\\release",
        "-IC:\\Users\\vanish\\Desktop\\курсач\\build-course_work-Desktop_Qt_6_4_0_MinGW_64_bit-Release",
        "-IC:\\Qt\\6.4.0\\mingw_64\\mkspecs\\win32-g++",
        "-isystem",
        "C:\\Qt\\Tools\\mingw1120_64\\lib\\gcc\\x86_64-w64-mingw32\\11.2.0\\include\\c++",
        "-isystem",
        "C:\\Qt\\Tools\\mingw1120_64\\lib\\gcc\\x86_64-w64-mingw32\\11.2.0\\include\\c++\\x86_64-w64-mingw32",
        "-isystem",
        "C:\\Qt\\Tools\\mingw1120_64\\lib\\gcc\\x86_64-w64-mingw32\\11.2.0\\include\\c++\\backward",
        "-isystem",
        "C:\\Qt\\Tools\\QtCreator\\bin\\clang\\lib\\clang\\14.0.3\\include",
        "-isystem",
        "C:\\Qt\\Tools\\mingw1120_64\\x86_64-w64-mingw32\\include",
        "-fmessage-length=0",
        "-fdiagnostics-show-note-include-stack",
        "-fretain-comments-from-system-headers",
        "-fmacro-backtrace-limit=0",
        "-ferror-limit=1000",
        "-x",
        "c++",
        "C:\\Users\\vanish\\Desktop\\курсач\\course_work\\findtab.cpp"
    ],
    "directory": "C:/Users/vanish/Desktop/курсач/build-course_work-Desktop_Qt_6_4_0_MinGW_64_bit-Release/.qtc_clangd",
    "file": "C:/Users/vanish/Desktop/курсач/course_work/findtab.cpp"
},
{
    "arguments": [
        "clang",
        "-Wno-documentation-unknown-command",
        "-Wno-unknown-warning-option",
        "-Wno-unknown-pragmas",
        "-nostdinc",
        "-nostdinc++",
        "-std=gnu++1z",
        "-Wall",
        "-Wextra",
        "-Wextra",
        "-fexceptions",
        "-mthreads",
        "-fsyntax-only",
        "-m64",
        "--target=x86_64-w64-mingw32",
        "-DUNICODE",
        "-D_UNICODE",
        "-DWIN32",
        "-DMINGW_HAS_SECURE_API",
        "-DQT_NO_DEBUG",
        "-DQT_WIDGETS_LIB",
        "-DQT_GUI_LIB",
        "-DQT_CORE_LIB",
        "-DQT_NEEDS_QMAIN",
        "-DQ_CREATOR_RUN",
        "-IC:\\Qt\\Tools\\QtCreator\\share\\qtcreator\\cplusplus\\wrappedMingwHeaders",
        "-IC:\\Qt\\Tools\\QtCreator\\share\\qtcreator\\cplusplus\\wrappedQtHeaders",
        "-IC:\\Qt\\Tools\\QtCreator\\share\\qtcreator\\cplusplus\\wrappedQtHeaders\\QtCore",
        "-IC:\\Users\\vanish\\Desktop\\курсач\\course_work",
        "-IC:\\Qt\\6.4.0\\mingw_64\\include",
        "-IC:\\Qt\\6.4.0\\mingw_64\\include\\QtWidgets",
        "-IC:\\Qt\\6.4.0\\mingw_64\\include\\QtGui",
        "-IC:\\Qt\\6.4.0\\mingw_64\\include\\QtCore",
        "-IC:\\Users\\vanish\\Desktop\\курсач\\build-course_work-Desktop_Qt_6_4_0_MinGW_64_bit-Release\\release",
        "-IC:\\Users\\vanish\\Desktop\\курсач\\build-course_work-Desktop_Qt_6_4_0_MinGW_64_bit-Release",
        "-IC:\\Qt\\6.4.0\\mingw_64\\mkspecs\\win32-g++",
        "-isystem",
        "C:\\Qt\\Tools\\mingw1120_64\\lib\\gcc\\x86_64-w64-mingw32\\11.2.0\\include\\c++",
        "-isystem",
        "C:\\Qt\\Tools\\mingw1120_64\\lib\\gcc\\x86_64-w64-mingw32\\11.2.0\\include\\c++\\x86_64-w64-mingw32",
        "-isystem",
        "C:\\Qt\\Tools\\mingw1120_64\\lib\\gcc\\x86_64-w64-mingw32\\11.2.0\\include\\c++\\backward",
        "-isystem",
        "C:\\Qt\\Tools\\QtCreator\\bin\\clang\\lib\\clang\\14.0.3\\include",
        "-isystem",
        "C:\\Qt\\Tools\\mingw1120_64\\x86_64-w64-mingw32\\include",
        "-fmessage-length=0",
        "-fdiagnostics-show-note-include-stack",
        "-fretain-comments-from-system-headers",
        "-fmacro-backtrace-limit=0",
        "-ferror-limit=1000",
        "-x",
        "c++",
        "C:\\Users\\vanish\\Desktop\\курсач\\course_work\\main.cpp"
    ],
    "directory": "C:/Users/vanish/Desktop/курсач/build-course_work-Desktop_Qt_6_4_0_MinGW_64_bit-Release/.qtc_clangd",
    "file": "C:/Users/vanish/Desktop/курсач/course_work/main.cpp"
},
{
    "arguments": [
        "clang",
        "-Wno-documentation-unknown-command",
        "-Wno-unknown-warning-option",
        "-Wno-unknown-pragmas",
        "-nostdinc",
        "-nostdinc++",
        "-std=gnu++1z",
        "-Wall",
        "-Wextra",
        "-Wextra",
        "-fexceptions",
        "-mthreads",
        "-fsyntax-only",
        "-m64",
        "--target=x86_64-w64-mingw32",
        "-DUNICODE",
        "-D_UNICODE",
        "-DWIN32",
        "-DMINGW_HAS_SECURE_API",
        "-DQT_NO_DEBUG",
        "-DQT_WIDGETS_LIB",
        "-DQT_GUI_LIB",
        "-DQT_CORE_LIB",
        "-DQT_NEEDS_QMAIN",
        "-DQ_CREATOR_RUN",
        "-IC:\\Qt\\Tools\\QtCreator\\share\\qtcreator\\cplusplus\\wrappedMingwHeaders",
        "-IC:\\Qt\\Tools\\QtCreator\\share\\qtcreator\\cplusplus\\wrappedQtHeaders",
        "-IC:\\Qt\\Tools\\QtCreator\\share\\qtcreator\\cplusplus\\wrappedQtHeaders\\QtCore",
        "-IC:\\Users\\vanish\\Desktop\\курсач\\course_work",
        "-IC:\\Qt\\6.4.0\\mingw_64\\include",
        "-IC:\\Qt\\6.4.0\\mingw_64\\include\\QtWidgets",
        "-IC:\\Qt\\6.4.0\\mingw_64\\include\\QtGui",
        "-IC:\\Qt\\6.4.0\\mingw_64\\include\\QtCore",
        "-IC:\\Users\\vanish\\Desktop\\курсач\\build-course_work-Desktop_Qt_6_4_0_MinGW_64_bit-Release\\release",
        "-IC:\\Users\\vanish\\Desktop\\курсач\\build-course_work-Desktop_Qt_6_4_0_MinGW_64_bit-Release",
        "-IC:\\Qt\\6.4.0\\mingw_64\\mkspecs\\win32-g++",
        "-isystem",
        "C:\\Qt\\Tools\\mingw1120_64\\lib\\gcc\\x86_64-w64-mingw32\\11.2.0\\include\\c++",
        "-isystem",
        "C:\\Qt\\Tools\\mingw1120_64\\lib\\gcc\\x86_64-w64-mingw32\\11.2.0\\include\\c++\\x86_64-w64-mingw32",
        "-isystem",
        "C:\\Qt\\Tools\\mingw1120_64\\lib\\gcc\\x86_64-w64-mingw32\\11.2.0\\include\\c++\\backward",
        "-isystem",
        "C:\\Qt\\Tools\\QtCreator\\bin\\clang\\lib\\clang\\14.0.3\\include",
        "-isystem",
        "C:\\Qt\\Tools\\mingw1120_64\\x86_64-w64-mingw32\\include",
        "-fmessage-length=0",
        "-fdiagnostics-show-note-include-stack",
        "-fretain-comments-from-system-headers",
        "-fmacro-backtrace-limit=0",
        "-ferror-limit=1000",
        "-x",
        "c++",
        "C:\\Users\\vanish\\Desktop\\курсач\\course_work\\mainwindow.cpp"
    ],
    "directory": "C:/Users/vanish/Desktop/курсач/build-course_work-Desktop_Qt_6_4_0_MinGW_64_bit-Release/.qtc_clangd",
    "file": "C:/Users/vanish/Desktop/курсач/course_work/mainwindow.cpp"
},
{
    "arguments": [
        "clang",
        "-Wno-documentation-unknown-command",
        "-Wno-unknown-warning-option",
        "-Wno-unknown-pragmas",
        "-nostdinc",
        "-nostdinc++",
        "-std=gnu++1z",
        "-Wall",
        "-Wextra",
        "-Wextra",
        "-fexceptions",
        "-mthreads",
        "-fsyntax-only",
        "-m64",
        "--target=x86_64-w64-mingw32",
        "-DUNICODE",
        "-D_UNICODE",
        "-DWIN32",
        "-DMINGW_HAS_SECURE_API",
        "-DQT_NO_DEBUG",
        "-DQT_WIDGETS_LIB",
        "-DQT_GUI_LIB",
        "-DQT_CORE_LIB",
        "-DQT_NEEDS_QMAIN",
        "-DQ_CREATOR_RUN",
        "-IC:\\Qt\\Tools\\QtCreator\\share\\qtcreator\\cplusplus\\wrappedMingwHeaders",
        "-IC:\\Qt\\Tools\\QtCreator\\share\\qtcreator\\cplusplus\\wrappedQtHeaders",
        "-IC:\\Qt\\Tools\\QtCreator\\share\\qtcreator\\cplusplus\\wrappedQtHeaders\\QtCore",
        "-IC:\\Users\\vanish\\Desktop\\курсач\\course_work",
        "-IC:\\Qt\\6.4.0\\mingw_64\\include",
        "-IC:\\Qt\\6.4.0\\mingw_64\\include\\QtWidgets",
        "-IC:\\Qt\\6.4.0\\mingw_64\\include\\QtGui",
        "-IC:\\Qt\\6.4.0\\mingw_64\\include\\QtCore",
        "-IC:\\Users\\vanish\\Desktop\\курсач\\build-course_work-Desktop_Qt_6_4_0_MinGW_64_bit-Release\\release",
        "-IC:\\Users\\vanish\\Desktop\\курсач\\build-course_work-Desktop_Qt_6_4_0_MinGW_64_bit-Release",
        "-IC:\\Qt\\6.4.0\\mingw_64\\mkspecs\\win32-g++",
        "-isystem",
        "C:\\Qt\\Tools\\mingw1120_64\\lib\\gcc\\x86_64-w64-mingw32\\11.2.0\\include\\c++",
        "-isystem",
        "C:\\Qt\\Tools\\mingw1120_64\\lib\\gcc\\x86_64-w64-mingw32\\11.2.0\\include\\c++\\x86_64-w64-mingw32",
        "-isystem",
        "C:\\Qt\\Tools\\mingw1120_64\\lib\\gcc\\x86_64-w64-mingw32\\11.2.0\\include\\c++\\backward",
        "-isystem",
        "C:\\Qt\\Tools\\QtCreator\\bin\\clang\\lib\\clang\\14.0.3\\include",
        "-isystem",
        "C:\\Qt\\Tools\\mingw1120_64\\x86_64-w64-mingw32\\include",
        "-fmessage-length=0",
        "-fdiagnostics-show-note-include-stack",
        "-fretain-comments-from-system-headers",
        "-fmacro-backtrace-limit=0",
        "-ferror-limit=1000",
        "-x",
        "c++",
        "C:\\Users\\vanish\\Desktop\\курсач\\course_work\\newaddresstab.cpp"
    ],
    "directory": "C:/Users/vanish/Desktop/курсач/build-course_work-Desktop_Qt_6_4_0_MinGW_64_bit-Release/.qtc_clangd",
    "file": "C:/Users/vanish/Desktop/курсач/course_work/newaddresstab.cpp"
},
{
    "arguments": [
        "clang",
        "-Wno-documentation-unknown-command",
        "-Wno-unknown-warning-option",
        "-Wno-unknown-pragmas",
        "-nostdinc",
        "-nostdinc++",
        "-std=gnu++1z",
        "-Wall",
        "-Wextra",
        "-Wextra",
        "-fexceptions",
        "-mthreads",
        "-fsyntax-only",
        "-m64",
        "--target=x86_64-w64-mingw32",
        "-DUNICODE",
        "-D_UNICODE",
        "-DWIN32",
        "-DMINGW_HAS_SECURE_API",
        "-DQT_NO_DEBUG",
        "-DQT_WIDGETS_LIB",
        "-DQT_GUI_LIB",
        "-DQT_CORE_LIB",
        "-DQT_NEEDS_QMAIN",
        "-DQ_CREATOR_RUN",
        "-IC:\\Qt\\Tools\\QtCreator\\share\\qtcreator\\cplusplus\\wrappedMingwHeaders",
        "-IC:\\Qt\\Tools\\QtCreator\\share\\qtcreator\\cplusplus\\wrappedQtHeaders",
        "-IC:\\Qt\\Tools\\QtCreator\\share\\qtcreator\\cplusplus\\wrappedQtHeaders\\QtCore",
        "-IC:\\Users\\vanish\\Desktop\\курсач\\course_work",
        "-IC:\\Qt\\6.4.0\\mingw_64\\include",
        "-IC:\\Qt\\6.4.0\\mingw_64\\include\\QtWidgets",
        "-IC:\\Qt\\6.4.0\\mingw_64\\include\\QtGui",
        "-IC:\\Qt\\6.4.0\\mingw_64\\include\\QtCore",
        "-IC:\\Users\\vanish\\Desktop\\курсач\\build-course_work-Desktop_Qt_6_4_0_MinGW_64_bit-Release\\release",
        "-IC:\\Users\\vanish\\Desktop\\курсач\\build-course_work-Desktop_Qt_6_4_0_MinGW_64_bit-Release",
        "-IC:\\Qt\\6.4.0\\mingw_64\\mkspecs\\win32-g++",
        "-isystem",
        "C:\\Qt\\Tools\\mingw1120_64\\lib\\gcc\\x86_64-w64-mingw32\\11.2.0\\include\\c++",
        "-isystem",
        "C:\\Qt\\Tools\\mingw1120_64\\lib\\gcc\\x86_64-w64-mingw32\\11.2.0\\include\\c++\\x86_64-w64-mingw32",
        "-isystem",
        "C:\\Qt\\Tools\\mingw1120_64\\lib\\gcc\\x86_64-w64-mingw32\\11.2.0\\include\\c++\\backward",
        "-isystem",
        "C:\\Qt\\Tools\\QtCreator\\bin\\clang\\lib\\clang\\14.0.3\\include",
        "-isystem",
        "C:\\Qt\\Tools\\mingw1120_64\\x86_64-w64-mingw32\\include",
        "-fmessage-length=0",
        "-fdiagnostics-show-note-include-stack",
        "-fretain-comments-from-system-headers",
        "-fmacro-backtrace-limit=0",
        "-ferror-limit=1000",
        "-x",
        "c++",
        "C:\\Users\\vanish\\Desktop\\курсач\\course_work\\tablemodel.cpp"
    ],
    "directory": "C:/Users/vanish/Desktop/курсач/build-course_work-Desktop_Qt_6_4_0_MinGW_64_bit-Release/.qtc_clangd",
    "file": "C:/Users/vanish/Desktop/курсач/course_work/tablemodel.cpp"
},
{
    "arguments": [
        "clang",
        "-Wno-documentation-unknown-command",
        "-Wno-unknown-warning-option",
        "-Wno-unknown-pragmas",
        "-nostdinc",
        "-nostdinc++",
        "-std=gnu++1z",
        "-Wall",
        "-Wextra",
        "-Wextra",
        "-fexceptions",
        "-mthreads",
        "-fsyntax-only",
        "-m64",
        "--target=x86_64-w64-mingw32",
        "-DUNICODE",
        "-D_UNICODE",
        "-DWIN32",
        "-DMINGW_HAS_SECURE_API",
        "-DQT_NO_DEBUG",
        "-DQT_WIDGETS_LIB",
        "-DQT_GUI_LIB",
        "-DQT_CORE_LIB",
        "-DQT_NEEDS_QMAIN",
        "-DQ_CREATOR_RUN",
        "-IC:\\Qt\\Tools\\QtCreator\\share\\qtcreator\\cplusplus\\wrappedMingwHeaders",
        "-IC:\\Qt\\Tools\\QtCreator\\share\\qtcreator\\cplusplus\\wrappedQtHeaders",
        "-IC:\\Qt\\Tools\\QtCreator\\share\\qtcreator\\cplusplus\\wrappedQtHeaders\\QtCore",
        "-IC:\\Users\\vanish\\Desktop\\курсач\\course_work",
        "-IC:\\Qt\\6.4.0\\mingw_64\\include",
        "-IC:\\Qt\\6.4.0\\mingw_64\\include\\QtWidgets",
        "-IC:\\Qt\\6.4.0\\mingw_64\\include\\QtGui",
        "-IC:\\Qt\\6.4.0\\mingw_64\\include\\QtCore",
        "-IC:\\Users\\vanish\\Desktop\\курсач\\build-course_work-Desktop_Qt_6_4_0_MinGW_64_bit-Release\\release",
        "-IC:\\Users\\vanish\\Desktop\\курсач\\build-course_work-Desktop_Qt_6_4_0_MinGW_64_bit-Release",
        "-IC:\\Qt\\6.4.0\\mingw_64\\mkspecs\\win32-g++",
        "-isystem",
        "C:\\Qt\\Tools\\mingw1120_64\\lib\\gcc\\x86_64-w64-mingw32\\11.2.0\\include\\c++",
        "-isystem",
        "C:\\Qt\\Tools\\mingw1120_64\\lib\\gcc\\x86_64-w64-mingw32\\11.2.0\\include\\c++\\x86_64-w64-mingw32",
        "-isystem",
        "C:\\Qt\\Tools\\mingw1120_64\\lib\\gcc\\x86_64-w64-mingw32\\11.2.0\\include\\c++\\backward",
        "-isystem",
        "C:\\Qt\\Tools\\QtCreator\\bin\\clang\\lib\\clang\\14.0.3\\include",
        "-isystem",
        "C:\\Qt\\Tools\\mingw1120_64\\x86_64-w64-mingw32\\include",
        "-fmessage-length=0",
        "-fdiagnostics-show-note-include-stack",
        "-fretain-comments-from-system-headers",
        "-fmacro-backtrace-limit=0",
        "-ferror-limit=1000",
        "-x",
        "c++-header",
        "C:\\Users\\vanish\\Desktop\\курсач\\course_work\\adddialog.h"
    ],
    "directory": "C:/Users/vanish/Desktop/курсач/build-course_work-Desktop_Qt_6_4_0_MinGW_64_bit-Release/.qtc_clangd",
    "file": "C:/Users/vanish/Desktop/курсач/course_work/adddialog.h"
},
{
    "arguments": [
        "clang",
        "-Wno-documentation-unknown-command",
        "-Wno-unknown-warning-option",
        "-Wno-unknown-pragmas",
        "-nostdinc",
        "-nostdinc++",
        "-std=gnu++1z",
        "-Wall",
        "-Wextra",
        "-Wextra",
        "-fexceptions",
        "-mthreads",
        "-fsyntax-only",
        "-m64",
        "--target=x86_64-w64-mingw32",
        "-DUNICODE",
        "-D_UNICODE",
        "-DWIN32",
        "-DMINGW_HAS_SECURE_API",
        "-DQT_NO_DEBUG",
        "-DQT_WIDGETS_LIB",
        "-DQT_GUI_LIB",
        "-DQT_CORE_LIB",
        "-DQT_NEEDS_QMAIN",
        "-DQ_CREATOR_RUN",
        "-IC:\\Qt\\Tools\\QtCreator\\share\\qtcreator\\cplusplus\\wrappedMingwHeaders",
        "-IC:\\Qt\\Tools\\QtCreator\\share\\qtcreator\\cplusplus\\wrappedQtHeaders",
        "-IC:\\Qt\\Tools\\QtCreator\\share\\qtcreator\\cplusplus\\wrappedQtHeaders\\QtCore",
        "-IC:\\Users\\vanish\\Desktop\\курсач\\course_work",
        "-IC:\\Qt\\6.4.0\\mingw_64\\include",
        "-IC:\\Qt\\6.4.0\\mingw_64\\include\\QtWidgets",
        "-IC:\\Qt\\6.4.0\\mingw_64\\include\\QtGui",
        "-IC:\\Qt\\6.4.0\\mingw_64\\include\\QtCore",
        "-IC:\\Users\\vanish\\Desktop\\курсач\\build-course_work-Desktop_Qt_6_4_0_MinGW_64_bit-Release\\release",
        "-IC:\\Users\\vanish\\Desktop\\курсач\\build-course_work-Desktop_Qt_6_4_0_MinGW_64_bit-Release",
        "-IC:\\Qt\\6.4.0\\mingw_64\\mkspecs\\win32-g++",
        "-isystem",
        "C:\\Qt\\Tools\\mingw1120_64\\lib\\gcc\\x86_64-w64-mingw32\\11.2.0\\include\\c++",
        "-isystem",
        "C:\\Qt\\Tools\\mingw1120_64\\lib\\gcc\\x86_64-w64-mingw32\\11.2.0\\include\\c++\\x86_64-w64-mingw32",
        "-isystem",
        "C:\\Qt\\Tools\\mingw1120_64\\lib\\gcc\\x86_64-w64-mingw32\\11.2.0\\include\\c++\\backward",
        "-isystem",
        "C:\\Qt\\Tools\\QtCreator\\bin\\clang\\lib\\clang\\14.0.3\\include",
        "-isystem",
        "C:\\Qt\\Tools\\mingw1120_64\\x86_64-w64-mingw32\\include",
        "-fmessage-length=0",
        "-fdiagnostics-show-note-include-stack",
        "-fretain-comments-from-system-headers",
        "-fmacro-backtrace-limit=0",
        "-ferror-limit=1000",
        "-x",
        "c++-header",
        "C:\\Users\\vanish\\Desktop\\курсач\\course_work\\addresswidget.h"
    ],
    "directory": "C:/Users/vanish/Desktop/курсач/build-course_work-Desktop_Qt_6_4_0_MinGW_64_bit-Release/.qtc_clangd",
    "file": "C:/Users/vanish/Desktop/курсач/course_work/addresswidget.h"
},
{
    "arguments": [
        "clang",
        "-Wno-documentation-unknown-command",
        "-Wno-unknown-warning-option",
        "-Wno-unknown-pragmas",
        "-nostdinc",
        "-nostdinc++",
        "-std=gnu++1z",
        "-Wall",
        "-Wextra",
        "-Wextra",
        "-fexceptions",
        "-mthreads",
        "-fsyntax-only",
        "-m64",
        "--target=x86_64-w64-mingw32",
        "-DUNICODE",
        "-D_UNICODE",
        "-DWIN32",
        "-DMINGW_HAS_SECURE_API",
        "-DQT_NO_DEBUG",
        "-DQT_WIDGETS_LIB",
        "-DQT_GUI_LIB",
        "-DQT_CORE_LIB",
        "-DQT_NEEDS_QMAIN",
        "-DQ_CREATOR_RUN",
        "-IC:\\Qt\\Tools\\QtCreator\\share\\qtcreator\\cplusplus\\wrappedMingwHeaders",
        "-IC:\\Qt\\Tools\\QtCreator\\share\\qtcreator\\cplusplus\\wrappedQtHeaders",
        "-IC:\\Qt\\Tools\\QtCreator\\share\\qtcreator\\cplusplus\\wrappedQtHeaders\\QtCore",
        "-IC:\\Users\\vanish\\Desktop\\курсач\\course_work",
        "-IC:\\Qt\\6.4.0\\mingw_64\\include",
        "-IC:\\Qt\\6.4.0\\mingw_64\\include\\QtWidgets",
        "-IC:\\Qt\\6.4.0\\mingw_64\\include\\QtGui",
        "-IC:\\Qt\\6.4.0\\mingw_64\\include\\QtCore",
        "-IC:\\Users\\vanish\\Desktop\\курсач\\build-course_work-Desktop_Qt_6_4_0_MinGW_64_bit-Release\\release",
        "-IC:\\Users\\vanish\\Desktop\\курсач\\build-course_work-Desktop_Qt_6_4_0_MinGW_64_bit-Release",
        "-IC:\\Qt\\6.4.0\\mingw_64\\mkspecs\\win32-g++",
        "-isystem",
        "C:\\Qt\\Tools\\mingw1120_64\\lib\\gcc\\x86_64-w64-mingw32\\11.2.0\\include\\c++",
        "-isystem",
        "C:\\Qt\\Tools\\mingw1120_64\\lib\\gcc\\x86_64-w64-mingw32\\11.2.0\\include\\c++\\x86_64-w64-mingw32",
        "-isystem",
        "C:\\Qt\\Tools\\mingw1120_64\\lib\\gcc\\x86_64-w64-mingw32\\11.2.0\\include\\c++\\backward",
        "-isystem",
        "C:\\Qt\\Tools\\QtCreator\\bin\\clang\\lib\\clang\\14.0.3\\include",
        "-isystem",
        "C:\\Qt\\Tools\\mingw1120_64\\x86_64-w64-mingw32\\include",
        "-fmessage-length=0",
        "-fdiagnostics-show-note-include-stack",
        "-fretain-comments-from-system-headers",
        "-fmacro-backtrace-limit=0",
        "-ferror-limit=1000",
        "-x",
        "c++-header",
        "C:\\Users\\vanish\\Desktop\\курсач\\course_work\\finddialog.h"
    ],
    "directory": "C:/Users/vanish/Desktop/курсач/build-course_work-Desktop_Qt_6_4_0_MinGW_64_bit-Release/.qtc_clangd",
    "file": "C:/Users/vanish/Desktop/курсач/course_work/finddialog.h"
},
{
    "arguments": [
        "clang",
        "-Wno-documentation-unknown-command",
        "-Wno-unknown-warning-option",
        "-Wno-unknown-pragmas",
        "-nostdinc",
        "-nostdinc++",
        "-std=gnu++1z",
        "-Wall",
        "-Wextra",
        "-Wextra",
        "-fexceptions",
        "-mthreads",
        "-fsyntax-only",
        "-m64",
        "--target=x86_64-w64-mingw32",
        "-DUNICODE",
        "-D_UNICODE",
        "-DWIN32",
        "-DMINGW_HAS_SECURE_API",
        "-DQT_NO_DEBUG",
        "-DQT_WIDGETS_LIB",
        "-DQT_GUI_LIB",
        "-DQT_CORE_LIB",
        "-DQT_NEEDS_QMAIN",
        "-DQ_CREATOR_RUN",
        "-IC:\\Qt\\Tools\\QtCreator\\share\\qtcreator\\cplusplus\\wrappedMingwHeaders",
        "-IC:\\Qt\\Tools\\QtCreator\\share\\qtcreator\\cplusplus\\wrappedQtHeaders",
        "-IC:\\Qt\\Tools\\QtCreator\\share\\qtcreator\\cplusplus\\wrappedQtHeaders\\QtCore",
        "-IC:\\Users\\vanish\\Desktop\\курсач\\course_work",
        "-IC:\\Qt\\6.4.0\\mingw_64\\include",
        "-IC:\\Qt\\6.4.0\\mingw_64\\include\\QtWidgets",
        "-IC:\\Qt\\6.4.0\\mingw_64\\include\\QtGui",
        "-IC:\\Qt\\6.4.0\\mingw_64\\include\\QtCore",
        "-IC:\\Users\\vanish\\Desktop\\курсач\\build-course_work-Desktop_Qt_6_4_0_MinGW_64_bit-Release\\release",
        "-IC:\\Users\\vanish\\Desktop\\курсач\\build-course_work-Desktop_Qt_6_4_0_MinGW_64_bit-Release",
        "-IC:\\Qt\\6.4.0\\mingw_64\\mkspecs\\win32-g++",
        "-isystem",
        "C:\\Qt\\Tools\\mingw1120_64\\lib\\gcc\\x86_64-w64-mingw32\\11.2.0\\include\\c++",
        "-isystem",
        "C:\\Qt\\Tools\\mingw1120_64\\lib\\gcc\\x86_64-w64-mingw32\\11.2.0\\include\\c++\\x86_64-w64-mingw32",
        "-isystem",
        "C:\\Qt\\Tools\\mingw1120_64\\lib\\gcc\\x86_64-w64-mingw32\\11.2.0\\include\\c++\\backward",
        "-isystem",
        "C:\\Qt\\Tools\\QtCreator\\bin\\clang\\lib\\clang\\14.0.3\\include",
        "-isystem",
        "C:\\Qt\\Tools\\mingw1120_64\\x86_64-w64-mingw32\\include",
        "-fmessage-length=0",
        "-fdiagnostics-show-note-include-stack",
        "-fretain-comments-from-system-headers",
        "-fmacro-backtrace-limit=0",
        "-ferror-limit=1000",
        "-x",
        "c++-header",
        "C:\\Users\\vanish\\Desktop\\курсач\\course_work\\findtab.h"
    ],
    "directory": "C:/Users/vanish/Desktop/курсач/build-course_work-Desktop_Qt_6_4_0_MinGW_64_bit-Release/.qtc_clangd",
    "file": "C:/Users/vanish/Desktop/курсач/course_work/findtab.h"
},
{
    "arguments": [
        "clang",
        "-Wno-documentation-unknown-command",
        "-Wno-unknown-warning-option",
        "-Wno-unknown-pragmas",
        "-nostdinc",
        "-nostdinc++",
        "-std=gnu++1z",
        "-Wall",
        "-Wextra",
        "-Wextra",
        "-fexceptions",
        "-mthreads",
        "-fsyntax-only",
        "-m64",
        "--target=x86_64-w64-mingw32",
        "-DUNICODE",
        "-D_UNICODE",
        "-DWIN32",
        "-DMINGW_HAS_SECURE_API",
        "-DQT_NO_DEBUG",
        "-DQT_WIDGETS_LIB",
        "-DQT_GUI_LIB",
        "-DQT_CORE_LIB",
        "-DQT_NEEDS_QMAIN",
        "-DQ_CREATOR_RUN",
        "-IC:\\Qt\\Tools\\QtCreator\\share\\qtcreator\\cplusplus\\wrappedMingwHeaders",
        "-IC:\\Qt\\Tools\\QtCreator\\share\\qtcreator\\cplusplus\\wrappedQtHeaders",
        "-IC:\\Qt\\Tools\\QtCreator\\share\\qtcreator\\cplusplus\\wrappedQtHeaders\\QtCore",
        "-IC:\\Users\\vanish\\Desktop\\курсач\\course_work",
        "-IC:\\Qt\\6.4.0\\mingw_64\\include",
        "-IC:\\Qt\\6.4.0\\mingw_64\\include\\QtWidgets",
        "-IC:\\Qt\\6.4.0\\mingw_64\\include\\QtGui",
        "-IC:\\Qt\\6.4.0\\mingw_64\\include\\QtCore",
        "-IC:\\Users\\vanish\\Desktop\\курсач\\build-course_work-Desktop_Qt_6_4_0_MinGW_64_bit-Release\\release",
        "-IC:\\Users\\vanish\\Desktop\\курсач\\build-course_work-Desktop_Qt_6_4_0_MinGW_64_bit-Release",
        "-IC:\\Qt\\6.4.0\\mingw_64\\mkspecs\\win32-g++",
        "-isystem",
        "C:\\Qt\\Tools\\mingw1120_64\\lib\\gcc\\x86_64-w64-mingw32\\11.2.0\\include\\c++",
        "-isystem",
        "C:\\Qt\\Tools\\mingw1120_64\\lib\\gcc\\x86_64-w64-mingw32\\11.2.0\\include\\c++\\x86_64-w64-mingw32",
        "-isystem",
        "C:\\Qt\\Tools\\mingw1120_64\\lib\\gcc\\x86_64-w64-mingw32\\11.2.0\\include\\c++\\backward",
        "-isystem",
        "C:\\Qt\\Tools\\QtCreator\\bin\\clang\\lib\\clang\\14.0.3\\include",
        "-isystem",
        "C:\\Qt\\Tools\\mingw1120_64\\x86_64-w64-mingw32\\include",
        "-fmessage-length=0",
        "-fdiagnostics-show-note-include-stack",
        "-fretain-comments-from-system-headers",
        "-fmacro-backtrace-limit=0",
        "-ferror-limit=1000",
        "-x",
        "c++-header",
        "C:\\Users\\vanish\\Desktop\\курсач\\course_work\\mainwindow.h"
    ],
    "directory": "C:/Users/vanish/Desktop/курсач/build-course_work-Desktop_Qt_6_4_0_MinGW_64_bit-Release/.qtc_clangd",
    "file": "C:/Users/vanish/Desktop/курсач/course_work/mainwindow.h"
},
{
    "arguments": [
        "clang",
        "-Wno-documentation-unknown-command",
        "-Wno-unknown-warning-option",
        "-Wno-unknown-pragmas",
        "-nostdinc",
        "-nostdinc++",
        "-std=gnu++1z",
        "-Wall",
        "-Wextra",
        "-Wextra",
        "-fexceptions",
        "-mthreads",
        "-fsyntax-only",
        "-m64",
        "--target=x86_64-w64-mingw32",
        "-DUNICODE",
        "-D_UNICODE",
        "-DWIN32",
        "-DMINGW_HAS_SECURE_API",
        "-DQT_NO_DEBUG",
        "-DQT_WIDGETS_LIB",
        "-DQT_GUI_LIB",
        "-DQT_CORE_LIB",
        "-DQT_NEEDS_QMAIN",
        "-DQ_CREATOR_RUN",
        "-IC:\\Qt\\Tools\\QtCreator\\share\\qtcreator\\cplusplus\\wrappedMingwHeaders",
        "-IC:\\Qt\\Tools\\QtCreator\\share\\qtcreator\\cplusplus\\wrappedQtHeaders",
        "-IC:\\Qt\\Tools\\QtCreator\\share\\qtcreator\\cplusplus\\wrappedQtHeaders\\QtCore",
        "-IC:\\Users\\vanish\\Desktop\\курсач\\course_work",
        "-IC:\\Qt\\6.4.0\\mingw_64\\include",
        "-IC:\\Qt\\6.4.0\\mingw_64\\include\\QtWidgets",
        "-IC:\\Qt\\6.4.0\\mingw_64\\include\\QtGui",
        "-IC:\\Qt\\6.4.0\\mingw_64\\include\\QtCore",
        "-IC:\\Users\\vanish\\Desktop\\курсач\\build-course_work-Desktop_Qt_6_4_0_MinGW_64_bit-Release\\release",
        "-IC:\\Users\\vanish\\Desktop\\курсач\\build-course_work-Desktop_Qt_6_4_0_MinGW_64_bit-Release",
        "-IC:\\Qt\\6.4.0\\mingw_64\\mkspecs\\win32-g++",
        "-isystem",
        "C:\\Qt\\Tools\\mingw1120_64\\lib\\gcc\\x86_64-w64-mingw32\\11.2.0\\include\\c++",
        "-isystem",
        "C:\\Qt\\Tools\\mingw1120_64\\lib\\gcc\\x86_64-w64-mingw32\\11.2.0\\include\\c++\\x86_64-w64-mingw32",
        "-isystem",
        "C:\\Qt\\Tools\\mingw1120_64\\lib\\gcc\\x86_64-w64-mingw32\\11.2.0\\include\\c++\\backward",
        "-isystem",
        "C:\\Qt\\Tools\\QtCreator\\bin\\clang\\lib\\clang\\14.0.3\\include",
        "-isystem",
        "C:\\Qt\\Tools\\mingw1120_64\\x86_64-w64-mingw32\\include",
        "-fmessage-length=0",
        "-fdiagnostics-show-note-include-stack",
        "-fretain-comments-from-system-headers",
        "-fmacro-backtrace-limit=0",
        "-ferror-limit=1000",
        "-x",
        "c++-header",
        "C:\\Users\\vanish\\Desktop\\курсач\\course_work\\newaddresstab.h"
    ],
    "directory": "C:/Users/vanish/Desktop/курсач/build-course_work-Desktop_Qt_6_4_0_MinGW_64_bit-Release/.qtc_clangd",
    "file": "C:/Users/vanish/Desktop/курсач/course_work/newaddresstab.h"
},
{
    "arguments": [
        "clang",
        "-Wno-documentation-unknown-command",
        "-Wno-unknown-warning-option",
        "-Wno-unknown-pragmas",
        "-nostdinc",
        "-nostdinc++",
        "-std=gnu++1z",
        "-Wall",
        "-Wextra",
        "-Wextra",
        "-fexceptions",
        "-mthreads",
        "-fsyntax-only",
        "-m64",
        "--target=x86_64-w64-mingw32",
        "-DUNICODE",
        "-D_UNICODE",
        "-DWIN32",
        "-DMINGW_HAS_SECURE_API",
        "-DQT_NO_DEBUG",
        "-DQT_WIDGETS_LIB",
        "-DQT_GUI_LIB",
        "-DQT_CORE_LIB",
        "-DQT_NEEDS_QMAIN",
        "-DQ_CREATOR_RUN",
        "-IC:\\Qt\\Tools\\QtCreator\\share\\qtcreator\\cplusplus\\wrappedMingwHeaders",
        "-IC:\\Qt\\Tools\\QtCreator\\share\\qtcreator\\cplusplus\\wrappedQtHeaders",
        "-IC:\\Qt\\Tools\\QtCreator\\share\\qtcreator\\cplusplus\\wrappedQtHeaders\\QtCore",
        "-IC:\\Users\\vanish\\Desktop\\курсач\\course_work",
        "-IC:\\Qt\\6.4.0\\mingw_64\\include",
        "-IC:\\Qt\\6.4.0\\mingw_64\\include\\QtWidgets",
        "-IC:\\Qt\\6.4.0\\mingw_64\\include\\QtGui",
        "-IC:\\Qt\\6.4.0\\mingw_64\\include\\QtCore",
        "-IC:\\Users\\vanish\\Desktop\\курсач\\build-course_work-Desktop_Qt_6_4_0_MinGW_64_bit-Release\\release",
        "-IC:\\Users\\vanish\\Desktop\\курсач\\build-course_work-Desktop_Qt_6_4_0_MinGW_64_bit-Release",
        "-IC:\\Qt\\6.4.0\\mingw_64\\mkspecs\\win32-g++",
        "-isystem",
        "C:\\Qt\\Tools\\mingw1120_64\\lib\\gcc\\x86_64-w64-mingw32\\11.2.0\\include\\c++",
        "-isystem",
        "C:\\Qt\\Tools\\mingw1120_64\\lib\\gcc\\x86_64-w64-mingw32\\11.2.0\\include\\c++\\x86_64-w64-mingw32",
        "-isystem",
        "C:\\Qt\\Tools\\mingw1120_64\\lib\\gcc\\x86_64-w64-mingw32\\11.2.0\\include\\c++\\backward",
        "-isystem",
        "C:\\Qt\\Tools\\QtCreator\\bin\\clang\\lib\\clang\\14.0.3\\include",
        "-isystem",
        "C:\\Qt\\Tools\\mingw1120_64\\x86_64-w64-mingw32\\include",
        "-fmessage-length=0",
        "-fdiagnostics-show-note-include-stack",
        "-fretain-comments-from-system-headers",
        "-fmacro-backtrace-limit=0",
        "-ferror-limit=1000",
        "-x",
        "c++-header",
        "C:\\Users\\vanish\\Desktop\\курсач\\course_work\\tablemodel.h"
    ],
    "directory": "C:/Users/vanish/Desktop/курсач/build-course_work-Desktop_Qt_6_4_0_MinGW_64_bit-Release/.qtc_clangd",
    "file": "C:/Users/vanish/Desktop/курсач/course_work/tablemodel.h"
},
{
    "arguments": [
        "clang",
        "-Wno-documentation-unknown-command",
        "-Wno-unknown-warning-option",
        "-Wno-unknown-pragmas",
        "-nostdinc",
        "-nostdinc++",
        "-std=gnu++1z",
        "-Wall",
        "-Wextra",
        "-Wextra",
        "-fexceptions",
        "-mthreads",
        "-fsyntax-only",
        "-m64",
        "--target=x86_64-w64-mingw32",
        "-DUNICODE",
        "-D_UNICODE",
        "-DWIN32",
        "-DMINGW_HAS_SECURE_API",
        "-DQT_NO_DEBUG",
        "-DQT_WIDGETS_LIB",
        "-DQT_GUI_LIB",
        "-DQT_CORE_LIB",
        "-DQT_NEEDS_QMAIN",
        "-DQ_CREATOR_RUN",
        "-IC:\\Qt\\Tools\\QtCreator\\share\\qtcreator\\cplusplus\\wrappedMingwHeaders",
        "-IC:\\Qt\\Tools\\QtCreator\\share\\qtcreator\\cplusplus\\wrappedQtHeaders",
        "-IC:\\Qt\\Tools\\QtCreator\\share\\qtcreator\\cplusplus\\wrappedQtHeaders\\QtCore",
        "-IC:\\Users\\vanish\\Desktop\\курсач\\course_work",
        "-IC:\\Qt\\6.4.0\\mingw_64\\include",
        "-IC:\\Qt\\6.4.0\\mingw_64\\include\\QtWidgets",
        "-IC:\\Qt\\6.4.0\\mingw_64\\include\\QtGui",
        "-IC:\\Qt\\6.4.0\\mingw_64\\include\\QtCore",
        "-IC:\\Users\\vanish\\Desktop\\курсач\\build-course_work-Desktop_Qt_6_4_0_MinGW_64_bit-Release\\release",
        "-IC:\\Users\\vanish\\Desktop\\курсач\\build-course_work-Desktop_Qt_6_4_0_MinGW_64_bit-Release",
        "-IC:\\Qt\\6.4.0\\mingw_64\\mkspecs\\win32-g++",
        "-isystem",
        "C:\\Qt\\Tools\\mingw1120_64\\lib\\gcc\\x86_64-w64-mingw32\\11.2.0\\include\\c++",
        "-isystem",
        "C:\\Qt\\Tools\\mingw1120_64\\lib\\gcc\\x86_64-w64-mingw32\\11.2.0\\include\\c++\\x86_64-w64-mingw32",
        "-isystem",
        "C:\\Qt\\Tools\\mingw1120_64\\lib\\gcc\\x86_64-w64-mingw32\\11.2.0\\include\\c++\\backward",
        "-isystem",
        "C:\\Qt\\Tools\\QtCreator\\bin\\clang\\lib\\clang\\14.0.3\\include",
        "-isystem",
        "C:\\Qt\\Tools\\mingw1120_64\\x86_64-w64-mingw32\\include",
        "-fmessage-length=0",
        "-fdiagnostics-show-note-include-stack",
        "-fretain-comments-from-system-headers",
        "-fmacro-backtrace-limit=0",
        "-ferror-limit=1000",
        "-x",
        "c++-header",
        "C:\\Users\\vanish\\Desktop\\курсач\\build-course_work-Desktop_Qt_6_4_0_MinGW_64_bit-Release\\ui_mainwindow.h"
    ],
    "directory": "C:/Users/vanish/Desktop/курсач/build-course_work-Desktop_Qt_6_4_0_MinGW_64_bit-Release/.qtc_clangd",
    "file": "C:/Users/vanish/Desktop/курсач/build-course_work-Desktop_Qt_6_4_0_MinGW_64_bit-Release/ui_mainwindow.h"
}
]